openFourier/__init__.py
openFourier/main.py
openFourier-0.1.3.dist-info/METADATA
openFourier-0.1.3.dist-info/WHEEL
openFourier-0.1.3.dist-info/top_level.txt
openFourier-0.1.3.dist-info/RECORD
