Metadata-Version: 2.2
Name: openFourier
Version: 0.1.3
Summary: A package for computing 2D Fourier transform amplitude spectrum
Home-page: https://github.com/bemoregt/openFourier
Author: WonwooPark
Author-email: bemore.one@gmail.com
Classifier: Programming Language :: Python :: 3
Classifier: License :: OSI Approved :: MIT License
Classifier: Operating System :: OS Independent
Requires-Python: >=3.8
Requires-Dist: numpy>=1.19.0
Dynamic: author
Dynamic: author-email
Dynamic: classifier
Dynamic: description
Dynamic: description-content-type
Dynamic: home-page
Dynamic: requires-dist
Dynamic: requires-python
Dynamic: summary
